README.md
setup.py
leverj_ordersigner/__init__.py
leverj_ordersigner/futures.py
leverj_ordersigner/spot.py
leverj_ordersigner.egg-info/PKG-INFO
leverj_ordersigner.egg-info/SOURCES.txt
leverj_ordersigner.egg-info/dependency_links.txt
leverj_ordersigner.egg-info/requires.txt
leverj_ordersigner.egg-info/top_level.txt