Metadata-Version: 2.1
Name: leverj-ordersigner
Version: 0.9.0
Summary: Python module for signing Leverj spot and derivatives exchange orders
Home-page: https://leverj.io
Author: leverj
License: MIT
Project-URL: Source, https://github.com/leverj/leverj-ordersigner
Platform: UNKNOWN
Classifier: Programming Language :: Python :: 3
Classifier: License :: OSI Approved :: MIT License
Classifier: Operating System :: OS Independent
Requires-Python: >=3.0
Provides-Extra: dev
